cms/__init__.py
cms/admin.py
cms/apps.py
cms/fixtures/simple_page.json
cms/fixtures/user.json
cms/locale/de/LC_MESSAGES/django.po
cms/migrations/0001_initial.py
cms/migrations/0002_auto_20190507_1532.py
cms/migrations/0003_auto_20200507_1739.py
cms/migrations/0004_auto_20200609_1640.py
cms/migrations/__init__.py
cms/models.py
cms/templates/base_cms.html
cms/templates/cms/content_page.html
cms/templates/cms/glossary_page.html
cms/templates/cms/index_page.html
cms/tests.py
cms/urls.py
cms/views.py
importer/Notes.md
importer/__init__.py
importer/admin.py
importer/apps.py
importer/cli.py
importer/fixtures/cron.json
importer/fixtures/duplicate_meetings_some_id.json
importer/fixtures/duplicate_meetings_with_id.json
importer/fixtures/duplicate_meetings_without_id.json
importer/fixtures/file-analysis.json
importer/fixtures/import-anything.json
importer/functions.py
importer/import_json.py
importer/importer.py
importer/json_datatypes.py
importer/json_to_db.py
importer/loader.py
importer/locale/de/LC_MESSAGES/django.po
importer/management/__init__.py
importer/management/commands/__init__.py
importer/management/commands/_import_base_command.py
importer/management/commands/benchmark_importer.py
importer/management/commands/cron.py
importer/management/commands/fix_sort_date.py
importer/management/commands/import.py
importer/management/commands/import_anything.py
importer/management/commands/import_body.py
importer/management/commands/import_clear.py
importer/management/commands/import_fetch.py
importer/management/commands/import_files.py
importer/management/commands/import_json.py
importer/management/commands/import_list.py
importer/management/commands/import_objects.py
importer/management/commands/import_retry.py
importer/management/commands/import_update.py
importer/management/commands/remove_body.py
importer/management/commands/set_cache_to_reimport.py
importer/migrations/0001_initial.py
importer/migrations/0002_auto_20190108_2242.py
importer/migrations/__init__.py
meine_stadt_transparent-0.2.14.dist-info/entry_points.txt
meine_stadt_transparent-0.2.14.dist-info/WHEEL
meine_stadt_transparent-0.2.14.dist-info/METADATA
meine_stadt_transparent-0.2.14.dist-info/RECORD
