Metadata-Version: 2.1
Name: meine-stadt-transparent
Version: 0.2.14
Summary: A website to bring municipal politics to citizens
License: MIT
Author: Tobias Hößl
Author-email: tobias@hoessl.eu
Requires-Python: >=3.8,<4.0
Classifier: License :: OSI Approved :: MIT License
Classifier: Programming Language :: Python :: 3
Classifier: Programming Language :: Python :: 3.10
Classifier: Programming Language :: Python :: 3.8
Classifier: Programming Language :: Python :: 3.9
Provides-Extra: import-json
Provides-Extra: pgp
Requires-Dist: Django (>=4.0.6,<4.1.0)
Requires-Dist: PyPDF2 (>=2.9.0,<3.0.0)
Requires-Dist: Wand (>=0.6.0,<0.7.0)
Requires-Dist: cattrs (>=22.1.0,<23.0.0); extra == "import-json"
Requires-Dist: django-allauth (>=0.51,<0.52)
Requires-Dist: django-anymail[mailjet,sendgrid] (>=8.1,<9.0)
Requires-Dist: django-decorator-include (>=2.1,<4.0)
Requires-Dist: django-elasticsearch-dsl (>=7.1,<7.3)
Requires-Dist: django-environ (>=0.9.0,<0.10.0)
Requires-Dist: django-geojson (>=3.0,<4.0)
Requires-Dist: django-q[sentry] (>=1.3.9,<2.0.0)
Requires-Dist: django-settings-export (>=1.2,<2.0)
Requires-Dist: django-simple-history (>=3.0,<4.0)
Requires-Dist: django-webpack-loader (>=1.6.0,<1.7.0)
Requires-Dist: django-widget-tweaks (>=1.4,<2.0)
Requires-Dist: django_csp (>=3.4,<4.0)
Requires-Dist: elasticsearch (==7.10.1)
Requires-Dist: elasticsearch-dsl (>=7.3,<8.0)
Requires-Dist: geoextract (>=0.3.1,<0.4.0)
Requires-Dist: geopy (>=2.0.0,<3.0.0)
Requires-Dist: gunicorn (>=20.0,<21.0)
Requires-Dist: html2text (>=2019.8,<2021.0)
Requires-Dist: icalendar (>=4.0,<5.0)
Requires-Dist: jsonfield (>=3.1,<4.0)
Requires-Dist: minio (>=5,<8)
Requires-Dist: mysqlclient (>=1.3,<3.0)
Requires-Dist: osm2geojson (>=0.2.0,<0.3.0)
Requires-Dist: pgpy (>=0.5.2,<0.6.0); extra == "pgp"
Requires-Dist: psycopg2 (>=2.9.3,<3.0.0)
Requires-Dist: python-dateutil (>=2.7,<3.0)
Requires-Dist: python-slugify (>=5,<7)
Requires-Dist: requests (>=2.22,<3.0)
Requires-Dist: sentry-sdk (>=1.0.0,<2.0.0)
Requires-Dist: splinter (>=0.14,<0.18)
Requires-Dist: tqdm (>=4.29,<5.0)
Requires-Dist: wagtail (>=3.0,<3.1)
